afm_tools/__init__.py
afm_tools/background_correction.py
afm_tools/gdef_indent_analyzer.py
afm_tools/gdef_sticher.py
afm_tools/sticher_utils.py
gdef_reader/__init__.py
gdef_reader/gdef_data_strucutres.py
gdef_reader/gdef_importer.py
gdef_reader/gdef_measurement.py
gdef_reader/utils.py
gdef_reporter/__init__.py
gdef_reporter/_code_utils.py
gdef_reporter/gdef_plotter.py
gdef_reporter/gdef_reporter.py
gdef_reporter/gdef_reporter_utils.py
gdef_reporter/plotter_styles.py
gdef_reporter/plotter_utils.py
gdef_reporter/pptx_styles.py
GDEFReader-0.0.1a41.dist-info/LICENSE
GDEFReader-0.0.1a41.dist-info/METADATA
GDEFReader-0.0.1a41.dist-info/WHEEL
GDEFReader-0.0.1a41.dist-info/top_level.txt
GDEFReader-0.0.1a41.dist-info/RECORD
