Metadata-Version: 2.1
Name: GDEFReader
Version: 0.0.1a41
Summary: Tool to read/process *.gdf AFM measurement files
Home-page: https://github.com/natter1/gdef_reader
Author: Nathanael Jöhrmann
Author-email: 
License: MIT
Platform: UNKNOWN
Requires-Python: >=3.9
Requires-Dist: matplotlib
Requires-Dist: numpy
Requires-Dist: scipy
